{"1.0.4": ["nah", "n.a.hawes@cs.bham.ac.uk"], "1.1.0": ["nah", "n.a.hawes@cs.bham.ac.uk"], "1.0.6": ["nah", "n.a.hawes@cs.bham.ac.uk"], "1.0.0": ["nah", "n.a.hawes@cs.bham.ac.uk"], "1.0.1": ["nah", "n.a.hawes@cs.bham.ac.uk"], "1.0.2": ["nah", "n.a.hawes@cs.bham.ac.uk"], "1.0.5": ["nah", "n.a.hawes@cs.bham.ac.uk"], "0.0.15": ["nah", "n.a.hawes@cs.bham.ac.uk"], "0.0.14": ["nah", "n.a.hawes@cs.bham.ac.uk"], "0.0.16": ["nah", "n.a.hawes@cs.bham.ac.uk"], "0.0.11": ["nah", "n.a.hawes@cs.bham.ac.uk"], "0.0.10": ["nah", "n.a.hawes@cs.bham.ac.uk"], "0.0.13": ["nah", "n.a.hawes@cs.bham.ac.uk"], "0.0.12": ["nah", "n.a.hawes@cs.bham.ac.uk"], "0.1.1": ["nah", "n.a.hawes@cs.bham.ac.uk"], "0.1.2": ["nah", "n.a.hawes@cs.bham.ac.uk"], "0.0.19": ["nah", "n.a.hawes@cs.bham.ac.uk"], "0.0.18": ["nah", "n.a.hawes@cs.bham.ac.uk"], "0.0.5": ["nah", "n.a.hawes@cs.bham.ac.uk"], "0.0.4": ["nah", "n.a.hawes@cs.bham.ac.uk"], "0.0.7": ["nah", "n.a.hawes@cs.bham.ac.uk"], "0.0.6": ["nah", "n.a.hawes@cs.bham.ac.uk"], "0.0.1": ["nah", "n.a.hawes@cs.bham.ac.uk"], "0.0.3": ["nah", "n.a.hawes@cs.bham.ac.uk"], "1.0.3": ["nah", "n.a.hawes@cs.bham.ac.uk"], "0.0.9": ["nah", "n.a.hawes@cs.bham.ac.uk"], "0.0.8": ["nah", "n.a.hawes@cs.bham.ac.uk"], "0.0.20": ["nah", "n.a.hawes@cs.bham.ac.uk"], "0.0.21": ["nah", "n.a.hawes@cs.bham.ac.uk"], "0.0.22": ["nah", "n.a.hawes@cs.bham.ac.uk"], "0.0.23": ["nah", "n.a.hawes@cs.bham.ac.uk"], "0.0.24": ["nah", "n.a.hawes@cs.bham.ac.uk"], "0.0.25": ["nah", "n.a.hawes@cs.bham.ac.uk"], "0.0.26": ["nah", "n.a.hawes@cs.bham.ac.uk"]}